m_tg_utils/__init__.py
m_tg_utils/bot.py
m_tg_utils/configloader.py
m_tg_utils-0.2.0.dist-info/METADATA
m_tg_utils-0.2.0.dist-info/WHEEL
m_tg_utils-0.2.0.dist-info/RECORD
