Metadata-Version: 2.1
Name: m_tg_utils
Version: 0.2.0
Summary: 
Author: megahomyak
Author-email: g.megahomyak@gmail.com
Requires-Python: >=3.8,<4.0
Classifier: Programming Language :: Python :: 3
Classifier: Programming Language :: Python :: 3.8
Classifier: Programming Language :: Python :: 3.9
Classifier: Programming Language :: Python :: 3.10
Classifier: Programming Language :: Python :: 3.11
Classifier: Programming Language :: Python :: 3.12
Requires-Dist: aiogram (>=3.2.0,<4.0.0)
Requires-Dist: cson (>=0.8,<0.9)
